py_pytest/__init__.py
py_pytest-0.0.1.dist-info/LICENSE
py_pytest-0.0.1.dist-info/METADATA
py_pytest-0.0.1.dist-info/WHEEL
py_pytest-0.0.1.dist-info/top_level.txt
py_pytest-0.0.1.dist-info/RECORD
