Metadata-Version: 2.1
Name: py-pytest
Version: 0.0.1
Summary: test install myself package
Home-page: https://github.com/wxing2008666/py_test
Author: wxing
Author-email: wxing2008666@126.com
License: MIT
Platform: UNKNOWN
